presentation_mode.py
presentation_mode-0.1.2.dist-info/entry_points.txt
presentation_mode-0.1.2.dist-info/WHEEL
presentation_mode-0.1.2.dist-info/METADATA
presentation_mode-0.1.2.dist-info/RECORD
