Metadata-Version: 2.1
Name: presentation-mode
Version: 0.1.2
Summary: 
Author: Simon Brulhart
Author-email: simon@brulhart.me
Requires-Python: >=3.7,<4.0
Classifier: Programming Language :: Python :: 3
Classifier: Programming Language :: Python :: 3.7
Requires-Dist: DBussy (>=1.2,<2.0)
Requires-Dist: python-decouple (>=3.1,<4.0)
Requires-Dist: slackclient (>=2.1,<3.0)
